django_virtual_models/__init__.py
django_virtual_models/exceptions.py
django_virtual_models/fields.py
django_virtual_models/generic_views.py
django_virtual_models/py.typed
django_virtual_models/serializers.py
django_virtual_models/utils.py
django_virtual_models/prefetch/__init__.py
django_virtual_models/prefetch/exceptions.py
django_virtual_models/prefetch/hints.py
django_virtual_models/prefetch/serializer_optimization.py
django_virtual_models/query_capture/__init__.py
django_virtual_models/query_capture/capture.py
django_virtual_models/query_capture/utils.py
django_virtual_models-0.4.0.dist-info/licenses/LICENSE
django_virtual_models-0.4.0.dist-info/WHEEL
django_virtual_models-0.4.0.dist-info/METADATA
django_virtual_models-0.4.0.dist-info/RECORD
