Metadata-Version: 2.4
Name: django-virtual-models
Version: 0.4.0
Summary: Improve performance and maintainability with a prefetching layer in your Django / Django REST Framework project
Keywords: django,prefetch,performance,optimization
Author-email: "Flávio Juvenal (Vinta Software)" <flavio@vinta.com.br>
Requires-Python: >=3.8
Classifier: Development Status :: 4 - Beta
Classifier: Intended Audience :: Developers
Classifier: License :: OSI Approved :: MIT License
Classifier: Natural Language :: English
Classifier: Programming Language :: Python :: 3
Classifier: Programming Language :: Python :: 3.10
Classifier: Programming Language :: Python :: 3.11
Classifier: Programming Language :: Python :: 3.12
Classifier: Programming Language :: Python :: 3.13
License-File: LICENSE
Requires-Dist: django >=4.2
Requires-Dist: djangorestframework >=3.13.1
Requires-Dist: typing-extensions >=4.3.0
Requires-Dist: mypy ==1.3.0  ; extra == "dev"
Requires-Dist: autoflake >=2.1.1,<3.0.0 ; extra == "dev"
Requires-Dist: flake8 >=6.0.0,<7.0.0 ; extra == "dev"
Requires-Dist: black ==23.3.0 ; extra == "dev"
Requires-Dist: isort >=5.12.0,<6.0.0 ; extra == "dev"
Requires-Dist: pre-commit >=3.3.2,<4.0.0 ; extra == "dev"
Requires-Dist: mkdocs-material==8.5.6 ; extra == "doc"
Requires-Dist: django >= 4.2,<6.0 ; extra == "example"
Requires-Dist: pyyaml >= 6.0,<7.0 ; extra == "example"
Requires-Dist: pytest >=7.3.1,<8.0.0 ; extra == "test"
Requires-Dist: pytest-cov[toml] >=4.1.0,<5.0.0 ; extra == "test"
Requires-Dist: pytest-django >=4.5.2,<5.0.0 ; extra == "test"
Requires-Dist: tox >=4.5.2,<5.0.0 ; extra == "test"
Requires-Dist: model_bakery >=1.11.0,<2.0.0 ; extra == "test"
Project-URL: Documentation, https://vintasoftware.github.io/django-virtual-models/
Project-URL: Homepage, https://github.com/vintasoftware/django-virtual-models
Provides-Extra: dev
Provides-Extra: doc
Provides-Extra: example
Provides-Extra: test
